<?xml version="1.0"?>
<!-- This file is part of the sale_payment module for Tryton.
The COPYRIGHT file at the top level of this repository contains the full
copyright notices and license terms. -->
<data>
    <xpath
        expr="/form/field[@name='payment_amount']"
        position="after">
        <label name="tipo_p"/>
        <field name="tipo_p"/>
        <newline/>
        <label name="banco"/>
        <field name="banco"/>
        <label name="numero_cuenta"/>
        <field name="numero_cuenta"/>
        <label name="fecha_deposito_cheque"/>
        <field name="fecha_deposito_cheque"/>
        <label name="titular"/>
        <field name="titular"/>
        <label name="numero_cheque"/>
        <field name="numero_cheque"/>
        <newline/>
        <label name="numero_tarjeta"/>
        <field name="numero_tarjeta"/>
        <label name="lote"/>
        <field name="lote"/>
        <label name="tarjeta"/>
        <field name="tarjeta"/>
        <newline/>
        <label name="banco_deposito"/>
        <field name="banco_deposito"/>
        <label name="numero_cuenta_deposito"/>
        <field name="numero_cuenta_deposito"/>
        <label name="fecha_deposito"/>
        <field name="fecha_deposito"/>
        <label name="numero_deposito"/>
        <field name="numero_deposito"/>
        <newline/>
        <label name="recibido"/>
        <field name="recibido"/>
        <label name="cambio_cliente" />
        <field name="cambio_cliente"/>
        <field name="credito" invisible="1"/>
        <newline/>
        <field name="amount" invisible="1"/>
        <newline/>
    </xpath>
</data>
